txrequests/__init__.py
txrequests/sessions.py
txrequests-0.9.6.dist-info/DESCRIPTION.rst
txrequests-0.9.6.dist-info/METADATA
txrequests-0.9.6.dist-info/RECORD
txrequests-0.9.6.dist-info/WHEEL
txrequests-0.9.6.dist-info/metadata.json
txrequests-0.9.6.dist-info/top_level.txt
