Metadata-Version: 2.0
Name: txrequests
Version: 0.9.6
Summary: Asynchronous Python HTTP for Humans.
Home-page: https://github.com/tardyp/txrequests
Author: Pierre Tardy
Author-email: tardyp@gmail.com
License: Apache License v2
Platform: UNKNOWN
Classifier: Intended Audience :: Developers
Classifier: Natural Language :: English
Classifier: License :: OSI Approved :: Apache Software License
Classifier: Programming Language :: Python
Classifier: Programming Language :: Python :: 2.6
Classifier: Programming Language :: Python :: 2.7
Requires-Dist: requests (>=1.2.0)
Requires-Dist: twisted (>=9.0.0)
